goldenpond/__init__.py
goldenpond/goldenpond.py
goldenpond-0.5.0.dist-info/LICENSE
goldenpond-0.5.0.dist-info/METADATA
goldenpond-0.5.0.dist-info/WHEEL
goldenpond-0.5.0.dist-info/RECORD
