Metadata-Version: 2.3
Name: goldenpond
Version: 0.5.0
Summary: A Python library for interpreting the GoldenPond DSLs for making musical chord progressions and rhythmic musical lines.
License: GPL-3.0-or-later
Author: Phil Jones
Author-email: interstar@gmail.com
Requires-Python: >=3.6,<4.0
Classifier: License :: OSI Approved :: GNU General Public License v3 or later (GPLv3+)
Classifier: Programming Language :: Python :: 3
Classifier: Programming Language :: Python :: 3.6
Classifier: Programming Language :: Python :: 3.7
Classifier: Programming Language :: Python :: 3.8
Classifier: Programming Language :: Python :: 3.9
Classifier: Programming Language :: Python :: 3.10
Classifier: Programming Language :: Python :: 3.11
Classifier: Programming Language :: Python :: 3.12
Classifier: Programming Language :: Python :: 3.13
